mcl/__init__.py
mcl/infirmary/VERSION.txt
mcl/infirmary/__init__.py
mcl/infirmary/interfaces.py
mcl/infirmary/main.py
mcl/infirmary/resources.py
mcl/infirmary/utils.py
mcl/infirmary/views.py
mcl.infirmary-1.2.4.dist-info/LICENSE.txt
mcl.infirmary-1.2.4.dist-info/METADATA
mcl.infirmary-1.2.4.dist-info/WHEEL
mcl.infirmary-1.2.4.dist-info/entry_points.txt
mcl.infirmary-1.2.4.dist-info/top_level.txt
mcl.infirmary-1.2.4.dist-info/zip-safe
mcl.infirmary-1.2.4.dist-info/RECORD
