Metadata-Version: 2.1
Name: mcl.infirmary
Version: 1.2.4
Summary: 🏥 Infirmary: an API for Clinical Data for the Consortium for Molecular and Cellular Characterization of Screen-Detected Lesions
Home-page: https://github.com/MCLConsortium/mcl.infirmary
Author: Sean Kelly
Author-email: sean.kelly@jpl.nasa.gov
License: ALv2
Keywords: rest api web clinical data lesions cancer
Classifier: Development Status :: 3 - Alpha
Classifier: Environment :: Web Environment
Classifier: Framework :: Pyramid
Classifier: Framework :: Buildout
Classifier: Intended Audience :: Developers
Classifier: Intended Audience :: Healthcare Industry
Classifier: License :: OSI Approved :: Apache Software License
Classifier: Operating System :: OS Independent
Classifier: Programming Language :: Python :: 3
Classifier: Topic :: Database :: Front-Ends
Classifier: Topic :: Scientific/Engineering :: Bio-Informatics
License-File: LICENSE.txt
Requires-Dist: setuptools (==51.3.3)
Requires-Dist: pyramid (==1.9.4)
Requires-Dist: waitress (==1.4.4)
Requires-Dist: pyramid-beaker (==0.8)
Requires-Dist: pyramid-ldap (==0.3.1)
Requires-Dist: zope.component (==4.6.2)
Requires-Dist: zope.interface (==5.4.0)
Requires-Dist: mcl.sickbay (==1.2.4)
